openweathermap/__init__.py
openweathermap/main.py
openweathermap_simplified-0.0.1.dist-info/LICENSE
openweathermap_simplified-0.0.1.dist-info/METADATA
openweathermap_simplified-0.0.1.dist-info/WHEEL
openweathermap_simplified-0.0.1.dist-info/top_level.txt
openweathermap_simplified-0.0.1.dist-info/RECORD
