Metadata-Version: 2.1
Name: openweathermap-simplified
Version: 0.0.1
Summary: A simple, opinionated wrapper for the openweathermap.org API
Home-page: https://github.com/sebastiaan-lampo/openweathermap-api
Author: Sebastiaan Lampo
Author-email: sebastiaan.lampo@gmail.com
License: UNKNOWN
Project-URL: Bug Tracker, https://github.com/sebastiaan-lampo/openweathermap-api/issues
Platform: UNKNOWN
Classifier: Programming Language :: Python :: 3
Classifier: License :: OSI Approved :: GNU General Public License v3 or later (GPLv3+)
Classifier: Operating System :: OS Independent
Requires-Python: >=3.6
License-File: LICENSE
Requires-Dist: requests
